science_utils_k/__init__.py
science_utils_k/echarts/EChart.py
science_utils_k/echarts/EChartFactory.py
science_utils_k/echarts/LineChart.py
science_utils_k/echarts/__init__.py
science_utils_k/utils/Logger.py
science_utils_k/utils/__init__.py
science_utils_k/utils/princess.py
science_utils_k-0.0.6.dist-info/METADATA
science_utils_k-0.0.6.dist-info/WHEEL
science_utils_k-0.0.6.dist-info/top_level.txt
science_utils_k-0.0.6.dist-info/RECORD
