Metadata-Version: 2.1
Name: science-utils-k
Version: 0.0.6
Summary: 个人使用的科研工具包
Home-page: UNKNOWN
Author: kouguozhao
Author-email: kouguozhao@163.com
License: UNKNOWN
Platform: UNKNOWN
Classifier: Programming Language :: Python :: 3
Classifier: License :: OSI Approved :: MIT License
Classifier: Operating System :: OS Independent
